{"type": "Feature", "id": 12517582, "geometry": {"type": "Point", "coordinates": [20.25, 44.9417]}, "properties": {"woe:id": 12517582, "woe:parent_id": 535638, "woe:name": "Batajnica Airport", "woe:placetype": 14, "woe:placetype_name": "Airport", "woe:lang": "ENG", "iso:country": "RS", "meta:provider": ["geoplanet:7.3.1", "geoplanet:7.3.2", "geoplanet:7.4.0", "geoplanet:7.4.1", "geoplanet:7.5.1", "geoplanet:7.5.2", "geoplanet:7.6.0", "geoplanet:7.8.1", "geoplanet:7.9.0", "geoplanet:7.10.0", "geoplanet:8.0.0", "woeplanet:8.0.0"], "meta:indexed": "2020-08-20T20:19:21.978419", "woe:alias_ENG_V": ["YBT Airport", "YBT"], "meta:updated": "2020-10-14T11:11:11.875597", "woe:hierarchy": {"continent": 24865675, "country": 20069818, "town": 0, "planet": 1, "county": 56072644, "suburb": 0, "state": 29389205, "region": 0, "localadmin": 0}, "woe:timezone_id": 28350889, "woe:hash": "sryrsv3s7hn6", "woe:centroid": [20.25, 44.9417], "geom:latitude": 44.9417, "geom:longitude": 20.25, "geom:hash": "sryrsv3s7hn6", "woe:latitude": 44.9417, "geom:centroid": [20.25, 44.9417], "woe:longitude": 20.25, "woe:repo": "woeplanet-airport-rs", "geom:area": 0.0, "woe:scale": 19}}